nose_randomly.py
nose_randomly-1.2.6.dist-info/LICENSE
nose_randomly-1.2.6.dist-info/METADATA
nose_randomly-1.2.6.dist-info/WHEEL
nose_randomly-1.2.6.dist-info/entry_points.txt
nose_randomly-1.2.6.dist-info/top_level.txt
nose_randomly-1.2.6.dist-info/RECORD
