Metadata-Version: 2.1
Name: nose-randomly
Version: 1.2.6
Summary: Nose plugin to randomly order tests and control random.seed.
Home-page: https://github.com/adamchainz/nose-randomly
Author: Adam Johnson
Author-email: me@adamj.eu
License: BSD
Keywords: nose,random,randomize,randomise,randomly
Platform: UNKNOWN
Classifier: Development Status :: 7 - Inactive
Classifier: Intended Audience :: Developers
Classifier: License :: OSI Approved :: BSD License
Classifier: Natural Language :: English
Classifier: Programming Language :: Python :: 2
Classifier: Programming Language :: Python :: 2.7
Classifier: Programming Language :: Python :: 3
Classifier: Programming Language :: Python :: 3.3
Classifier: Programming Language :: Python :: 3.4
Classifier: Programming Language :: Python :: 3.5
Classifier: Programming Language :: Python :: 3.6
Requires-Python: >=2.7, !=3.0.*, !=3.1.*, !=3.2.*, !=3.3.*
Requires-Dist: nose
